{
    "id": 52004392758,
    "owner": {
        "nsid": "194951624@N02",
        "username": "Joost J. Bakker IJmuiden",
        "path_alias": "joostjbakkerijmuiden"
    },
    "secret": "1a6693ebc1",
    "server": "65535",
    "farm": 66,
    "title": "Salix alba - White-willow, White willow, Ак-тал, Cricket-Bat Willow, European willow, Golden Willow, Sallow Tree, Water Willow",
    "ispublic": 1,
    "isfriend": 0,
    "isfamily": 0,
    "description": "",
    "dateupload": "1649952006",
    "views": 43,
    "tags": [],
    "media": "photo",
    "media_status": "ready",
    "date": "2022-04-14 16:00:06",
    "width": 6048,
    "height": 4032,
    "url": "https://live.staticflickr.com/65535/52004392758_4b5ff9c90f_o.jpg",
    "label": "Original",
    "search": {
        "text": "Salix alba",
        "license": "4,5,6,9,10"
    },
    "category": "flickr",
    "subcategory": "search",
    "filename": "52004392758_4b5ff9c90f_o_d",
    "extension": "jpg"
}
