{
    "id": 53549151481,
    "owner": {
        "nsid": "81269484@N00",
        "username": "JuliaC2006",
        "path_alias": "juliac2006"
    },
    "secret": "98419d8d59",
    "server": "65535",
    "farm": 66,
    "title": "Wild cherry",
    "ispublic": 1,
    "isfriend": 0,
    "isfamily": 0,
    "description": "The second of our monthly surveys - taking notes on what was appearing in the meadow. Saw lots of the regular birds, but of note were the many signs that Spring is close - flowers, insects, and some trees starting to pop into leaf.",
    "dateupload": "1708791072",
    "views": 137,
    "tags": [
        "wattsmeadow",
        "rochester",
        "white",
        "flower",
        "blossom",
        "cherry",
        "prunusavium"
    ],
    "media": "photo",
    "media_status": "ready",
    "date": "2024-02-24 16:11:12",
    "width": 1024,
    "height": 768,
    "url": "https://live.staticflickr.com/65535/53549151481_cd013f9eda_o.jpg",
    "label": "Original",
    "search": {
        "text": "Prunus avium",
        "license": "4,5,6,9,10"
    },
    "category": "flickr",
    "subcategory": "search",
    "filename": "53549151481_cd013f9eda_o_d",
    "extension": "jpg"
}
