{
    "id": 50021880881,
    "owner": {
        "nsid": "149164524@N06",
        "username": "janetgraham84new",
        "path_alias": null
    },
    "secret": "09ed082263",
    "server": "65535",
    "farm": 66,
    "title": "Eriophyes laevis galls on Alnus glutinosa, Tir Stent, North Wales, June 2020",
    "ispublic": 1,
    "isfriend": 0,
    "isfamily": 0,
    "description": "",
    "dateupload": "1592553031",
    "views": 152,
    "tags": [
        "eriophyes",
        "laevis"
    ],
    "media": "photo",
    "media_status": "ready",
    "date": "2020-06-19 07:50:31",
    "width": 3000,
    "height": 2000,
    "url": "https://live.staticflickr.com/65535/50021880881_f63baca915_o.jpg",
    "label": "Original",
    "search": {
        "text": "Alnus glutinosa",
        "license": "4,5,6,9,10"
    },
    "category": "flickr",
    "subcategory": "search",
    "filename": "50021880881_f63baca915_o_d",
    "extension": "jpg"
}
