{
    "id": 53323324307,
    "owner": {
        "nsid": "14829735@N00",
        "username": "dullhunk",
        "path_alias": "dullhunk"
    },
    "secret": "db66c3086d",
    "server": "65535",
    "farm": 66,
    "title": "Prestwich Clough",
    "ispublic": 1,
    "isfriend": 0,
    "isfamily": 0,
    "description": "",
    "dateupload": "1699703065",
    "views": 99,
    "tags": [
        "beech",
        "fagussylvatica"
    ],
    "media": "photo",
    "media_status": "ready",
    "date": "2023-11-11 11:44:25",
    "width": 2268,
    "height": 4032,
    "url": "https://live.staticflickr.com/65535/53323324307_8336a2bc5f_o.jpg",
    "label": "Original",
    "search": {
        "text": "Fagus sylvatica",
        "license": "4,5,6,9,10"
    },
    "category": "flickr",
    "subcategory": "search",
    "filename": "53323324307_8336a2bc5f_o_d",
    "extension": "jpg"
}
