{
    "id": 53815155589,
    "owner": {
        "nsid": "47343585@N00",
        "username": "jeremy_norbury",
        "path_alias": "norbury"
    },
    "secret": "3a8c300b11",
    "server": "65535",
    "farm": 66,
    "title": "IMG_0238",
    "ispublic": 1,
    "isfriend": 0,
    "isfamily": 0,
    "description": "Tilia cordata minor wiring",
    "dateupload": "1719316703",
    "views": 40,
    "tags": [
        "bonsai",
        "summer",
        "2024",
        "june"
    ],
    "media": "photo",
    "media_status": "ready",
    "date": "2024-06-25 11:58:23",
    "width": 6000,
    "height": 4000,
    "url": "https://live.staticflickr.com/65535/53815155589_e83a5c804e_o.jpg",
    "label": "Original",
    "search": {
        "text": "Tilia cordata",
        "license": "4,5,6,9,10"
    },
    "category": "flickr",
    "subcategory": "search",
    "filename": "53815155589_e83a5c804e_o_d",
    "extension": "jpg"
}
