{
    "id": 53891589123,
    "owner": {
        "nsid": "35478170@N08",
        "username": "Matt Lavin",
        "path_alias": "plant_diversity"
    },
    "secret": "aa8b0ce806",
    "server": "65535",
    "farm": 66,
    "title": "Pseudotsuga menziesii - Douglas fir",
    "ispublic": 1,
    "isfriend": 0,
    "isfamily": 0,
    "description": "Mature Douglas fir forming a fairly closed canopy and bordering mountain big sagebrush steppe at the southwest end of the Spanish Peaks near Jack Creek Road, Madison Range, Madison County, Montana. The mature Douglas fir forest here forms a distinct environment because of the distinction of the plant composition of the forest understory, which is exemplified by an abundance of fairly well developed shrubs of Vaccinium globulare, common huckleberry.",
    "dateupload": "1722357155",
    "views": 92,
    "tags": [
        "jackcreek",
        "moonlightbasin",
        "spanishpeaks",
        "madisonrange",
        "madisoncounty",
        "montana",
        "understory",
        "drysite",
        "pseudotsugamenziesii",
        "douglasfir",
        "pinaceae",
        "native",
        "tree",
        "plant",
        "biodiversity",
        "montanemeadow",
        "greateryellowstonearea"
    ],
    "media": "photo",
    "media_status": "ready",
    "date": "2024-07-30 16:32:35",
    "width": 4032,
    "height": 3024,
    "url": "https://live.staticflickr.com/65535/53891589123_ef7de10b03_o.jpg",
    "label": "Original",
    "search": {
        "text": "Pseudotsuga menziesii",
        "license": "4,5,6,9,10"
    },
    "category": "flickr",
    "subcategory": "search",
    "filename": "53891589123_ef7de10b03_o_d",
    "extension": "jpg"
}
