{
    "id": 49596479922,
    "owner": {
        "nsid": "149164524@N06",
        "username": "janetgraham84new",
        "path_alias": null
    },
    "secret": "470d6925a1",
    "server": "65535",
    "farm": 66,
    "title": "Andricus quercusradicis gall on Quercus petraea, Trawscoed, North Wales, 2019",
    "ispublic": 1,
    "isfriend": 0,
    "isfamily": 0,
    "description": "",
    "dateupload": "1582904459",
    "views": 128,
    "tags": [],
    "media": "photo",
    "media_status": "ready",
    "date": "2020-02-28 15:40:59",
    "width": 3000,
    "height": 2522,
    "url": "https://live.staticflickr.com/65535/49596479922_c9e43d44d6_o.jpg",
    "label": "Original",
    "search": {
        "text": "Quercus petraea",
        "license": "4,5,6,9,10"
    },
    "category": "flickr",
    "subcategory": "search",
    "filename": "49596479922_c9e43d44d6_o_d",
    "extension": "jpg"
}
