{
    "id": 53006062408,
    "owner": {
        "nsid": "26138378@N03",
        "username": "Patrick Clement.",
        "path_alias": null
    },
    "secret": "fe4a35bc4d",
    "server": "65535",
    "farm": 66,
    "title": "04.075  BF22 Etainia louisella mine",
    "ispublic": 1,
    "isfriend": 0,
    "isfamily": 0,
    "description": "Mine on samara of field maple, Acer campestre, Lutley Worcestershire, 24.6.23.",
    "dateupload": "1687876270",
    "views": 161,
    "tags": [],
    "media": "photo",
    "media_status": "ready",
    "date": "2023-06-27 14:31:10",
    "width": 5472,
    "height": 3648,
    "url": "https://live.staticflickr.com/65535/53006062408_2cce4d8954_o.jpg",
    "label": "Original",
    "search": {
        "text": "Acer campestre",
        "license": "4,5,6,9,10"
    },
    "category": "flickr",
    "subcategory": "search",
    "filename": "53006062408_2cce4d8954_o_d",
    "extension": "jpg"
}
