{
    "id": 49919874046,
    "owner": {
        "nsid": "61021753@N02",
        "username": "BioDivLibrary",
        "path_alias": "biodivlibrary"
    },
    "secret": "320892a997",
    "server": "65535",
    "farm": 66,
    "title": "n24_w1150",
    "ispublic": 1,
    "isfriend": 0,
    "isfamily": 0,
    "description": "Charakteristik der deutschen Holzgewächse im blattlosen Zustande\nMünchen :in der literarisch-artistischen Anstalt ,1829.\n<a href=\"https://biodiversitylibrary.org/page/35392043\" rel=\"noreferrer nofollow\">biodiversitylibrary.org/page/35392043</a>",
    "dateupload": "1590075788",
    "views": 5358,
    "tags": [
        "artist:name=sebastminsinger",
        "tree",
        "taxonomy:binomial=carpinusbetulus",
        "hornbeam",
        "birch",
        "taxonomy:binomial=fagussylvatica",
        "beech",
        "blattloserzustand",
        "gehölze",
        "germany",
        "woodyplants",
        "universitylibraryuniversityofillinoisurbanachampaign",
        "bhl:page=35392043",
        "dc:identifier=httpsbiodiversitylibraryorgpage35392043",
        "woodplants"
    ],
    "media": "photo",
    "media_status": "ready",
    "date": "2020-05-21 15:43:08",
    "width": 2292,
    "height": 3135,
    "url": "https://live.staticflickr.com/65535/49919874046_30b39377e0_o.jpg",
    "label": "Original",
    "search": {
        "text": "Carpinus betulus",
        "license": "4,5,6,9,10"
    },
    "category": "flickr",
    "subcategory": "search",
    "filename": "49919874046_30b39377e0_o_d",
    "extension": "jpg"
}
