{
    "id": 14651563771,
    "owner": {
        "nsid": "38601566@N00",
        "username": "niftyniall",
        "path_alias": "niftyniall"
    },
    "secret": "c2bae8c9d0",
    "server": "5502",
    "farm": 6,
    "title": "Cut-leaf Linden",
    "ispublic": 1,
    "isfriend": 0,
    "isfamily": 0,
    "description": "Tree <b>338</b> Tilia platyphyllos &quot;Laciniata&quot; Cut-leaf Linden",
    "dateupload": "1405363712",
    "views": 522,
    "tags": [
        "canada",
        "britishcolumbia",
        "coquitlam",
        "riverviewhospital",
        "essondalehospital"
    ],
    "media": "photo",
    "media_status": "ready",
    "date": "2014-07-14 18:48:32",
    "width": 1704,
    "height": 2272,
    "url": "https://live.staticflickr.com/5502/14651563771_7415564175_o.jpg",
    "label": "Original",
    "search": {
        "text": "Tilia platyphyllos",
        "license": "4,5,6,9,10"
    },
    "category": "flickr",
    "subcategory": "search",
    "filename": "14651563771_7415564175_o_d",
    "extension": "jpg"
}
